tradedesk/__init__.py
tradedesk/marketdata.py
tradedesk/py.typed
tradedesk/runner.py
tradedesk/strategy.py
tradedesk/subscriptions.py
tradedesk/indicators/__init__.py
tradedesk/indicators/adx.py
tradedesk/indicators/atr.py
tradedesk/indicators/base.py
tradedesk/indicators/bollinger_bands.py
tradedesk/indicators/cci.py
tradedesk/indicators/ema.py
tradedesk/indicators/macd.py
tradedesk/indicators/mfi.py
tradedesk/indicators/obv.py
tradedesk/indicators/rsi.py
tradedesk/indicators/sma.py
tradedesk/indicators/stochastic.py
tradedesk/indicators/vwap.py
tradedesk/indicators/williams_r.py
tradedesk/providers/__init__.py
tradedesk/providers/base.py
tradedesk/providers/backtest/__init__.py
tradedesk/providers/backtest/client.py
tradedesk/providers/backtest/reporting.py
tradedesk/providers/backtest/streamer.py
tradedesk/providers/ig/__init__.py
tradedesk/providers/ig/client.py
tradedesk/providers/ig/settings.py
tradedesk/providers/ig/streamer.py
tradedesk-0.2.0.dist-info/METADATA
tradedesk-0.2.0.dist-info/WHEEL
tradedesk-0.2.0.dist-info/licenses/LICENSE
tradedesk-0.2.0.dist-info/licenses/NOTICE
tradedesk-0.2.0.dist-info/RECORD
