Metadata-Version: 2.4
Name: tradedesk
Version: 0.2.0
Summary: Trading infrastructure library with backtesting
Project-URL: Homepage, https://github.com/radiusred
Project-URL: Repository, https://github.com/radiusred/tradedesk
Project-URL: Issues, https://github.com/radiusred/tradedesk/issues
Author-email: "Radius Red Ltd." <opensource@radiusred.uk>
Maintainer-email: "Radius Red Ltd." <opensource@radiusred.uk>
License-Expression: Apache-2.0
License-File: LICENSE
License-File: NOTICE
Classifier: Operating System :: OS Independent
Classifier: Programming Language :: Python :: 3
Requires-Python: >=3.11
Requires-Dist: aiohttp>=3.9.0
Requires-Dist: lightstreamer-client-lib>=2.0
Requires-Dist: numpy>=2.4.0
Requires-Dist: python-dotenv>=1.0
Requires-Dist: requests>=2.31
Provides-Extra: dev
Requires-Dist: mypy>=1.19; extra == 'dev'
Requires-Dist: pre-commit>=4.5; extra == 'dev'
Requires-Dist: pytest-asyncio>=0.23; extra == 'dev'
Requires-Dist: pytest-cov>=7.0; extra == 'dev'
Requires-Dist: pytest>=8.0; extra == 'dev'
Requires-Dist: responses>=0.25; extra == 'dev'
Requires-Dist: ruff>=0.14; extra == 'dev'
